tcc.sv
module tcc(doac,dowc,dowcr,mode,wci,done);
  input [7:0] doac,dowc,dowcr;
  input clk,wci;
  input [1:0] mode;
  output reg done;
  
  always @(mode or wci or doac or dowc or dowcr)
    casex({mode,wci})
      3'b00_0:done=(dowc===1);
      3'b00_1:done=(dowc===0);
      
      3'b01_0:done=(dowc+1===dowcr);
      3'b01_1:done=(dowc===dowcr);
      
      3'b10_x:done=(dowc===doac);
      
      3'b11_x:done=1'b0;
    endcase
endmodule

datamux.sv
module datamux(in1,in2,in3,seldata,clk,out);
  input [7:0] in1,in2,in3;
  input clk;
  input [1:0] seldata;
  output [7:0] out;
  
  assign out= ((seldata==2'b00) ? in1 : ((seldata==2'b01) ? in2 : in3));
  
endmodule

wordcnt.sv
module wordcnt(data,plwc,reswc,enw,incw,decw,clk,wci,wco,dowc);
  input [7:0] data;
  input plwc,reswc,enw,incw,decw,clk,wci;
  output wco;
  output reg [7:0] dowc;
  
  always @(posedge clk)
    begin
    if(reswc)
      dowc=8'b0;
  else
    if(plwc)
      dowc=data;
  else
    if(enw)
      if(incw && ~wci)
        begin
          dowc=dowc+1;
        end
  else
    if(decw)
      begin
        if(dowc==8'b0 && wci==1'b0)
          dowc=dowc-1;
        else
          if(dowc!=8'b0)
            dowc=dowc-1;
      end
      
    end
  
  assign wco = (~((dowc===8'hff) && incw && enw)) && (~((dowc===8'h00) && decw && enw)) || wci;

endmodule

mux1x2.sv
module mux1x2(din1,din2,sel,clk,out);
  input [7:0] din1,din2;
  input sel,clk;
  output [7:0] out;
  
  /*
  always @(posedge clk)
    if(sel)
      out=din2;
  else
    out=din1;
*/
  assign out=( sel ? din2 : din1);
  
endmodule

wordcntreg.sv
module wordcntreg(din,plwcr,clk,dowcr);
  input [7:0] din;
  input plwcr,clk;
  output reg [7:0] dowcr;
  
  always @(posedge clk)
    if(plwcr)
      dowcr=din;
  
endmodule

controlreg.sv
module controlreg(data,plcr,out,clk);
  input [2:0] data;
  input plcr,clk;
  output reg [2:0] out;
  
  always @(posedge clk)
    if(plcr)
      out=data;
endmodule

addrcnt.sv
module addrcnt(data,plac,ena,inca,deca,clk,aci,aco,doac);
  input [7:0] data;
  input plac,ena,inca,deca,clk,aci;
  output aco;
  output reg [7:0] doac;
  
  always @(posedge clk)
    begin
      if(plac)
      doac=data;
  else
    if(ena)
      if(inca && ~aci)
        begin
          doac=doac+1;
        end
  else
    if(deca)
      begin
        if(doac==8'b0 && aci==1'b0)
          doac=doac-1;
        else
          if(doac!=8'b0)
            doac=doac-1;
      end
      
    end

  assign aco = (~((doac===8'hff) && inca && ena)) && (~((doac===8'h00) && deca && ena)) || aci;
endmodule

addrreg.sv
module addrreg(din,plar,clk,doar);
  input [7:0] din;
  input plar,clk;
  output reg [7:0] doar;
  
  always @(posedge clk)
    if(plar)
      doar=din;
  
endmodule

decoder.sv
module decoder(instr,docr,clk,plar,plwr,plcr,plac,ena,inca,deca,reswc,plwc,enw,incw,decw,oedata,sela,selw,seldata);
  input [2:0] instr,docr;
  input clk;
  output reg plar,plwr,plcr,plac,ena,inca,deca,reswc,plwc,enw,incw,decw,oedata,sela,selw;
  output reg [1:0] seldata;

  always @(instr or docr)
    casex({instr,docr})
      6'b000_xxx:{plar,plwr,sela,selw,plcr,seldata,plac,ena,inca,deca,reswc,plwc,enw,incw,decw,oedata}=17'b0_0_0_0_1_00_0_0_0_0_0_0_0_0_0_0;
      
      6'b001_xxx:{plar,plwr,sela,selw,plcr,seldata,plac,ena,inca,deca,reswc,plwc,enw,incw,decw,oedata}=17'b0_0_0_0_0_10_0_0_0_0_0_0_0_0_0_1;
      
      6'b010_xxx:{plar,plwr,sela,selw,plcr,seldata,plac,ena,inca,deca,reswc,plwc,enw,incw,decw,oedata}=17'b0_0_0_0_0_01_0_0_0_0_0_0_0_0_0_1;
      
      6'b011_xxx:{plar,plwr,sela,selw,plcr,seldata,plac,ena,inca,deca,reswc,plwc,enw,incw,decw,oedata}=17'b0_0_0_0_0_00_0_0_0_0_0_0_0_0_0_1;
      
      6'b100_x01:{plar,plwr,sela,selw,plcr,seldata,plac,ena,inca,deca,reswc,plwc,enw,incw,decw,oedata}=17'b0_0_1_0_0_00_1_0_0_0_1_0_0_0_0_0;
      6'b100_x00:{plar,plwr,sela,selw,plcr,seldata,plac,ena,inca,deca,reswc,plwc,enw,incw,decw,oedata}=17'b0_0_1_1_0_00_1_0_0_0_0_1_0_0_0_0;
      6'b100_x10:{plar,plwr,sela,selw,plcr,seldata,plac,ena,inca,deca,reswc,plwc,enw,incw,decw,oedata}=17'b0_0_1_1_0_00_1_0_0_0_0_1_0_0_0_0;
      6'b100_x11:{plar,plwr,sela,selw,plcr,seldata,plac,ena,inca,deca,reswc,plwc,enw,incw,decw,oedata}=17'b0_0_1_1_0_00_1_0_0_0_0_1_0_0_0_0;
      
      6'b101_xxx:{plar,plwr,sela,selw,plcr,seldata,plac,ena,inca,deca,reswc,plwc,enw,incw,decw,oedata}=17'b1_0_0_0_0_00_1_0_0_0_0_0_0_0_0_0;
      
      6'b110_x01:{plar,plwr,sela,selw,plcr,seldata,plac,ena,inca,deca,reswc,plwc,enw,incw,decw,oedata}=17'b0_1_0_0_0_00_1_0_0_0_1_0_0_0_0_0;
      6'b110_x00:{plar,plwr,sela,selw,plcr,seldata,plac,ena,inca,deca,reswc,plwc,enw,incw,decw,oedata}=17'b0_1_0_0_0_00_0_0_0_0_0_1_0_0_0_0;
      6'b110_x10:{plar,plwr,sela,selw,plcr,seldata,plac,ena,inca,deca,reswc,plwc,enw,incw,decw,oedata}=17'b0_1_0_0_0_00_0_0_0_0_0_1_0_0_0_0;
      6'b110_x11:{plar,plwr,sela,selw,plcr,seldata,plac,ena,inca,deca,reswc,plwc,enw,incw,decw,oedata}=17'b0_1_0_0_0_00_0_0_0_0_0_1_0_0_0_0;
      
      6'b111_010:{plar,plwr,sela,selw,plcr,seldata,plac,ena,inca,deca,reswc,plwc,enw,incw,decw,oedata}=17'b0_0_0_0_0_00_0_1_1_0_0_0_0_0_0_0;
      6'b111_110:{plar,plwr,sela,selw,plcr,seldata,plac,ena,inca,deca,reswc,plwc,enw,incw,decw,oedata}=17'b0_0_0_0_0_00_0_1_0_1_0_0_0_0_0_0;
      6'b111_000:{plar,plwr,sela,selw,plcr,seldata,plac,ena,inca,deca,reswc,plwc,enw,incw,decw,oedata}=17'b0_0_0_0_0_00_0_1_1_0_0_0_1_0_1_0;
      6'b111_100:{plar,plwr,sela,selw,plcr,seldata,plac,ena,inca,deca,reswc,plwc,enw,incw,decw,oedata}=17'b0_0_0_0_0_00_0_1_0_1_0_0_1_0_1_0;
      6'b111_001:{plar,plwr,sela,selw,plcr,seldata,plac,ena,inca,deca,reswc,plwc,enw,incw,decw,oedata}=17'b0_0_0_0_0_00_0_1_1_0_0_0_1_1_0_0;
      6'b111_101:{plar,plwr,sela,selw,plcr,seldata,plac,ena,inca,deca,reswc,plwc,enw,incw,decw,oedata}=17'b0_0_0_0_0_00_0_1_0_1_0_0_1_1_0_0;
      6'b111_011:{plar,plwr,sela,selw,plcr,seldata,plac,ena,inca,deca,reswc,plwc,enw,incw,decw,oedata}=17'b0_0_0_0_0_00_0_1_1_0_0_0_1_1_0_0;
      6'b111_111:{plar,plwr,sela,selw,plcr,seldata,plac,ena,inca,deca,reswc,plwc,enw,incw,decw,oedata}=17'b0_0_0_0_0_00_0_1_0_1_0_0_1_1_0_0;
      
    endcase
endmodule

design.sv
module am2940(address,oeaddr,data,clk,aci,aco,wci,wco,done,instr);
  input [7:0] data;
  input oeaddr,clk,aci,wci;
  input [2:0] instr;
  output [7:0] address;
  output aco,wco,done;
  
  wire cr2,cr1,cr0,plar,plwr,plcr,plac,ena,inca,deca,reswc,plwc,enw,incw,decw,oedata,sela,selw;
  wire [1:0] seldata;
  wire [7:0] doar,domuxa,dowcr,doac,domuxw,dowc,dodm;
  wire [2:0] docr;
  
  decoder decoder_inst(instr,docr,clk,plar,plwr,plcr,plac,ena,inca,deca,reswc,plwc,enw,incw,decw,oedata,sela,selw,seldata);
  
  addrreg addrreg_inst(data,plar,clk,doar);
  mux1x2 mux1x2_addrreg_inst(data,doar,sela,clk,domuxa);
  addrcnt addrcnt_inst(domuxa,plac,ena,inca,deca,clk,aci,aco,doac);
  
  controlreg controlreg_inst(data[2:0],plcr,docr,clk);
  
  wordcntreg wordcntreg_inst(data,plwr,clk,dowcr);
  mux1x2 mux1x2_wordcntreg_inst(data,dowcr,selw,clk,domuxw);
  wordcnt wordcnt_inst(domuxw,plwc,reswc,enw,incw,decw,clk,wci,wco,dowc);
  
  datamux datamux_inst(doac,dowc,{5'b11111,docr},seldata,clk,dodm);
  
  tcc tcc_inst(doac,dowc,dowcr,docr[1:0],wci,done);
  
endmodule

testbench.sv
module test;
  reg [7:0] data;
  reg [2:0] instr;
  reg oeaddr,clk,aci,wci;
  wire [7:0] address;
  wire aco,wco,done;
  
  am2940 am2940_inst(address,oeaddr,data,clk,aci,aco,wci,wco,done,instr);
  
  
  initial
    begin
      #0 clk=1'b0;
      forever #5 clk=~clk;
    end
  
  initial
    #500 $finish;
  
  initial
    begin
      $dumpfile("dump.vcd");
      $dumpvars;
    end
  
  initial
    begin
      #0 data=8'b0;instr=3'b0;oeaddr=1'b0;aci=1'b0;wci=1'b0;instr=3'b001;
      #10 instr=3'b000;
      #10 data=8'b01100011;instr=3'b110;
      #10 data=8'b01101100;instr=3'b101;
      #10 instr=3'b111;
      #60 instr=3'b010;
      #10 instr=3'b011;
      #10 instr=3'b100;
      #10 instr=3'b010;
      #10 instr=3'b011;
    end
  
  
endmodule

dump.vcd
$date
	Fri Sep 23 11:28:55 2022
$end
$version
	Icarus Verilog
$end
$timescale
	1s
$end
$scope module test $end
$var wire 8 ! address [7:0] $end
$var wire 1 " wco $end
$var wire 1 # done $end
$var wire 1 $ aco $end
$var reg 1 % aci $end
$var reg 1 & clk $end
$var reg 8 ' data [7:0] $end
$var reg 3 ( instr [2:0] $end
$var reg 1 ) oeaddr $end
$var reg 1 * wci $end
$scope module am2940_inst $end
$var wire 1 % aci $end
$var wire 8 + address [7:0] $end
$var wire 1 & clk $end
$var wire 8 , data [7:0] $end
$var wire 3 - instr [2:0] $end
$var wire 1 ) oeaddr $end
$var wire 1 * wci $end
$var wire 1 " wco $end
$var wire 1 . selw $end
$var wire 2 / seldata [1:0] $end
$var wire 1 0 sela $end
$var wire 1 1 reswc $end
$var wire 1 2 plwr $end
$var wire 1 3 plwc $end
$var wire 1 4 plcr $end
$var wire 1 5 plar $end
$var wire 1 6 plac $end
$var wire 1 7 oedata $end
$var wire 1 8 incw $end
$var wire 1 9 inca $end
$var wire 1 : enw $end
$var wire 1 ; ena $end
$var wire 8 < dowcr [7:0] $end
$var wire 8 = dowc [7:0] $end
$var wire 1 # done $end
$var wire 8 > domuxw [7:0] $end
$var wire 8 ? domuxa [7:0] $end
$var wire 8 @ dodm [7:0] $end
$var wire 3 A docr [2:0] $end
$var wire 8 B doar [7:0] $end
$var wire 8 C doac [7:0] $end
$var wire 1 D decw $end
$var wire 1 E deca $end
$var wire 1 $ aco $end
$scope module addrcnt_inst $end
$var wire 1 % aci $end
$var wire 1 $ aco $end
$var wire 1 & clk $end
$var wire 1 6 plac $end
$var wire 1 9 inca $end
$var wire 1 ; ena $end
$var wire 1 E deca $end
$var wire 8 F data [7:0] $end
$var reg 8 G doac [7:0] $end
$upscope $end
$scope module addrreg_inst $end
$var wire 1 & clk $end
$var wire 8 H din [7:0] $end
$var wire 1 5 plar $end
$var reg 8 I doar [7:0] $end
$upscope $end
$scope module controlreg_inst $end
$var wire 1 & clk $end
$var wire 3 J data [2:0] $end
$var wire 1 4 plcr $end
$var reg 3 K out [2:0] $end
$upscope $end
$scope module datamux_inst $end
$var wire 1 & clk $end
$var wire 8 L in1 [7:0] $end
$var wire 8 M in3 [7:0] $end
$var wire 2 N seldata [1:0] $end
$var wire 8 O out [7:0] $end
$var wire 8 P in2 [7:0] $end
$upscope $end
$scope module decoder_inst $end
$var wire 1 & clk $end
$var wire 3 Q docr [2:0] $end
$var wire 3 R instr [2:0] $end
$var reg 1 E deca $end
$var reg 1 D decw $end
$var reg 1 ; ena $end
$var reg 1 : enw $end
$var reg 1 9 inca $end
$var reg 1 8 incw $end
$var reg 1 7 oedata $end
$var reg 1 6 plac $end
$var reg 1 5 plar $end
$var reg 1 4 plcr $end
$var reg 1 3 plwc $end
$var reg 1 2 plwr $end
$var reg 1 1 reswc $end
$var reg 1 0 sela $end
$var reg 2 S seldata [1:0] $end
$var reg 1 . selw $end
$upscope $end
$scope module mux1x2_addrreg_inst $end
$var wire 1 & clk $end
$var wire 8 T din1 [7:0] $end
$var wire 8 U din2 [7:0] $end
$var wire 1 0 sel $end
$var wire 8 V out [7:0] $end
$upscope $end
$scope module mux1x2_wordcntreg_inst $end
$var wire 1 & clk $end
$var wire 8 W din1 [7:0] $end
$var wire 1 . sel $end
$var wire 8 X out [7:0] $end
$var wire 8 Y din2 [7:0] $end
$upscope $end
$scope module tcc_inst $end
$var wire 1 Z clk $end
$var wire 8 [ doac [7:0] $end
$var wire 2 \ mode [1:0] $end
$var wire 1 * wci $end
$var wire 8 ] dowcr [7:0] $end
$var wire 8 ^ dowc [7:0] $end
$var reg 1 # done $end
$upscope $end
$scope module wordcnt_inst $end
$var wire 1 & clk $end
$var wire 8 _ data [7:0] $end
$var wire 1 D decw $end
$var wire 1 : enw $end
$var wire 1 8 incw $end
$var wire 1 3 plwc $end
$var wire 1 1 reswc $end
$var wire 1 * wci $end
$var wire 1 " wco $end
$var reg 8 ` dowc [7:0] $end
$upscope $end
$scope module wordcntreg_inst $end
$var wire 1 & clk $end
$var wire 8 a din [7:0] $end
$var wire 1 2 plwcr $end
$var reg 8 b dowcr [7:0] $end
$upscope $end
$upscope $end
$upscope $end
$enddefinitions $end
#0
$dumpvars
bx b
b0 a
bx `
b0 _
bx ^
bx ]
bx \
bx [
zZ
bx Y
b0 X
b0 W
b0 V
bx U
b0 T
b10 S
b1 R
bx Q
bx P
b11111xxx O
b10 N
b11111xxx M
bx L
bx K
b0 J
bx I
b0 H
bx G
b0 F
0E
0D
bx C
bx B
bx A
b11111xxx @
b0 ?
b0 >
bx =
bx <
0;
0:
09
08
17
06
05
04
03
02
01
00
b10 /
0.
b1 -
b0 ,
bz +
0*
0)
b1 (
b0 '
0&
0%
1$
0#
1"
bz !
$end
#5
1&
#10
bx @
bx O
14
b0 /
b0 N
b0 S
07
0&
b0 (
b0 -
b0 R
#15
b0 \
b11111000 M
b0 A
b0 K
b0 Q
1&
#20
12
04
13
b11 J
b1100011 ?
b1100011 F
b1100011 V
b1100011 >
b1100011 X
b1100011 _
0&
b110 (
b110 -
b110 R
b1100011 '
b1100011 ,
b1100011 H
b1100011 T
b1100011 W
b1100011 a
#25
b1100011 <
b1100011 Y
b1100011 ]
b1100011 b
b1100011 =
b1100011 P
b1100011 ^
b1100011 `
1&
#30
15
02
16
03
b100 J
b1101100 ?
b1101100 F
b1101100 V
b1101100 >
b1101100 X
b1101100 _
0&
b101 (
b101 -
b101 R
b1101100 '
b1101100 ,
b1101100 H
b1101100 T
b1101100 W
b1101100 a
#35
b1101100 @
b1101100 O
b1101100 C
b1101100 G
b1101100 L
b1101100 [
b1101100 B
b1101100 I
b1101100 U
1&
#40
05
06
1;
19
1:
1D
0&
b111 (
b111 -
b111 R
#45
b1101101 @
b1101101 O
b1101101 C
b1101101 G
b1101101 L
b1101101 [
b1100010 =
b1100010 P
b1100010 ^
b1100010 `
1&
#50
0&
#55
b1101110 @
b1101110 O
b1100001 =
b1100001 P
b1100001 ^
b1100001 `
b1101110 C
b1101110 G
b1101110 L
b1101110 [
1&
#60
0&
#65
b1101111 @
b1101111 O
b1101111 C
b1101111 G
b1101111 L
b1101111 [
b1100000 =
b1100000 P
b1100000 ^
b1100000 `
1&
#70
0&
#75
b1110000 @
b1110000 O
b1011111 =
b1011111 P
b1011111 ^
b1011111 `
b1110000 C
b1110000 G
b1110000 L
b1110000 [
1&
#80
0&
#85
b1110001 @
b1110001 O
b1110001 C
b1110001 G
b1110001 L
b1110001 [
b1011110 =
b1011110 P
b1011110 ^
b1011110 `
1&
#90
0&
#95
b1110010 @
b1110010 O
b1011101 =
b1011101 P
b1011101 ^
b1011101 `
b1110010 C
b1110010 G
b1110010 L
b1110010 [
1&
#100
b1011101 @
b1011101 O
b1 /
b1 N
b1 S
0;
09
0:
0D
17
0&
b10 (
b10 -
b10 R
#105
1&
#110
b1110010 @
b1110010 O
b0 /
b0 N
b0 S
0&
b11 (
b11 -
b11 R
#115
1&
#120
b1100011 >
b1100011 X
b1100011 _
10
1.
16
13
07
0&
b100 (
b100 -
b100 R
#125
b1101100 @
b1101100 O
b1101100 C
b1101100 G
b1101100 L
b1101100 [
b1100011 =
b1100011 P
b1100011 ^
b1100011 `
1&
#130
b1101100 >
b1101100 X
b1101100 _
b1100011 @
b1100011 O
00
0.
b1 /
b1 N
b1 S
06
03
17
0&
b10 (
b10 -
b10 R
#135
1&
#140
b1101100 @
b1101100 O
b0 /
b0 N
b0 S
0&
b11 (
b11 -
b11 R
